hpsspy/__init__.py
hpsspy/conftest.py
hpsspy/scan.py
hpsspy/util.py
hpsspy/data/desi.json
hpsspy/data/sdss.json
hpsspy/os/__init__.py
hpsspy/os/_os.py
hpsspy/os/path.py
hpsspy/test/__init__.py
hpsspy/test/test_data.py
hpsspy/test/test_os.py
hpsspy/test/test_scan.py
hpsspy/test/test_top_level.py
hpsspy/test/test_util.py
hpsspy/test/t/hpss_cache.csv
hpsspy/test/t/invalid_file
hpsspy/test/t/missing_cache.json
hpsspy/test/t/test_scan.json
hpsspy/test/t/test_scan_disk_cache.csv
hpsspy/test/t/test_scan_disk_cache_missing.csv
hpsspy/test/t/test_scan_disk_cache_multiple.csv
hpsspy-0.8.0.dist-info/licenses/LICENSE.rst
hpsspy-0.8.0.dist-info/METADATA
hpsspy-0.8.0.dist-info/WHEEL
hpsspy-0.8.0.dist-info/entry_points.txt
hpsspy-0.8.0.dist-info/top_level.txt
hpsspy-0.8.0.dist-info/RECORD
