Metadata-Version: 2.4
Name: hpsspy
Version: 0.8.0
Summary: Package for interacting with HPSS.
Author-email: Benjamin Alan Weaver <benjamin.weaver@noirlab.edu>
License-Expression: BSD-3-Clause
Project-URL: Documentation, https://hpsspy.readthedocs.io/en/stable/
Project-URL: Repository, https://github.com/weaverba137/hpsspy
Project-URL: Issues, https://github.com/weaverba137/hpsspy/issues
Project-URL: Changelog, https://hpsspy.readthedocs.io/en/stable/changes.html
Keywords: HPSS,tape,backup
Classifier: Development Status :: 5 - Production/Stable
Classifier: Environment :: Console
Classifier: Intended Audience :: Science/Research
Classifier: Intended Audience :: System Administrators
Classifier: Operating System :: OS Independent
Classifier: Programming Language :: Python :: 3
Classifier: Topic :: System :: Archiving
Classifier: Topic :: Utilities
Requires-Python: >=3.10
License-File: LICENSE.rst
Requires-Dist: pytz
Provides-Extra: test
Requires-Dist: pytest; extra == "test"
Provides-Extra: coverage
Requires-Dist: pytest-cov; extra == "coverage"
Requires-Dist: coveralls; extra == "coverage"
Provides-Extra: doc
Requires-Dist: Sphinx; extra == "doc"
Requires-Dist: sphinx-rtd-theme; extra == "doc"
Dynamic: license-file
